Metadata-Version: 2.1
Name: asciiTUI
Version: 1.2.8
Summary: This is a library of tools for you to use with your needs for an attractive type of terminal (console) display.
Home-page: https://github.com/azzammuhyala/asciiTUI
Author: azzammuhyala
Author-email: azzammuhyala@gmail.com
Keywords: asciiTUI,asciitui,ascii,tui,console,text-based,tools,attractive,terminal,basic-tools,text,art-ascii,remove_ansi,ansi,terminal_size,rgb,table,tabulate,progress_bar,justify,justifytext,justify-text,command_split,cmd_split,pwinput,basic,console-display
